dialectus/__init__.py
dialectus/engine/__init__.py
dialectus/engine/config/__init__.py
dialectus/engine/config/openrouter_filters.json
dialectus/engine/config/settings.py
dialectus/engine/debate_engine/__init__.py
dialectus/engine/debate_engine/context_builder.py
dialectus/engine/debate_engine/engine.py
dialectus/engine/debate_engine/judge_coordinator.py
dialectus/engine/debate_engine/models.py
dialectus/engine/debate_engine/prompt_builder.py
dialectus/engine/debate_engine/response_handler.py
dialectus/engine/debate_engine/round_manager.py
dialectus/engine/debate_engine/types.py
dialectus/engine/debate_engine/utils.py
dialectus/engine/formats/__init__.py
dialectus/engine/formats/base.py
dialectus/engine/formats/oxford.py
dialectus/engine/formats/parliamentary.py
dialectus/engine/formats/public_forum.py
dialectus/engine/formats/registry.py
dialectus/engine/formats/socratic.py
dialectus/engine/formats/topic_themes.py
dialectus/engine/judges/__init__.py
dialectus/engine/judges/ai_judge.py
dialectus/engine/judges/base.py
dialectus/engine/judges/ensemble_utils.py
dialectus/engine/judges/factory.py
dialectus/engine/models/__init__.py
dialectus/engine/models/base_types.py
dialectus/engine/models/cache_manager.py
dialectus/engine/models/manager.py
dialectus/engine/models/anthropic/__init__.py
dialectus/engine/models/anthropic/anthropic_enhanced_model_info.py
dialectus/engine/models/anthropic/anthropic_model.py
dialectus/engine/models/anthropic/anthropic_model_filter.py
dialectus/engine/models/anthropic/anthropic_pricing.py
dialectus/engine/models/openai/__init__.py
dialectus/engine/models/openai/openai_enhanced_model_info.py
dialectus/engine/models/openai/openai_model.py
dialectus/engine/models/openai/openai_model_filter.py
dialectus/engine/models/openai/openai_pricing.py
dialectus/engine/models/openrouter/openrouter_architecture.py
dialectus/engine/models/openrouter/openrouter_capability_extractor.py
dialectus/engine/models/openrouter/openrouter_enhanced_model_info.py
dialectus_engine-0.4.1.dist-info/licenses/LICENSE
dialectus_engine-0.4.1.dist-info/METADATA
dialectus_engine-0.4.1.dist-info/WHEEL
dialectus_engine-0.4.1.dist-info/top_level.txt
dialectus_engine-0.4.1.dist-info/RECORD
