Metadata-Version: 2.4
Name: dialectus-engine
Version: 0.4.1
Summary: Dialectus AI debate engine framework
Author: Dialectus AI
License-Expression: MIT
Project-URL: Homepage, https://github.com/dialectus-ai/dialectus-engine
Project-URL: Repository, https://github.com/dialectus-ai/dialectus-engine
Project-URL: Issues, https://github.com/dialectus-ai/dialectus-engine/issues
Keywords: ai,debate,llm,ollama,openrouter,artificial-intelligence
Classifier: Development Status :: 4 - Beta
Classifier: Intended Audience :: Developers
Classifier: Intended Audience :: Education
Classifier: Programming Language :: Python :: 3
Classifier: Programming Language :: Python :: 3.12
Classifier: Programming Language :: Python :: 3.13
Classifier: Programming Language :: Python :: 3.14
Classifier: Topic :: Scientific/Engineering :: Artificial Intelligence
Classifier: Topic :: Software Development :: Libraries :: Python Modules
Requires-Python: >=3.12
License-File: LICENSE
Requires-Dist: httpx>=0.28.1
Requires-Dist: openai>=1.105.0
Requires-Dist: pydantic>=2.11.7
Provides-Extra: dev
Requires-Dist: ruff>=0.5.0; extra == "dev"
Requires-Dist: pytest>=7.0; extra == "dev"
Requires-Dist: twine; extra == "dev"
Requires-Dist: build; extra == "dev"
Requires-Dist: pyright>=1.1.377; extra == "dev"
Dynamic: license-file
